cyberfusion/WordPressSupport/__init__.py
cyberfusion/WordPressSupport/cache.py
cyberfusion/WordPressSupport/config.py
cyberfusion/WordPressSupport/core.py
cyberfusion/WordPressSupport/database.py
cyberfusion/WordPressSupport/exceptions.py
cyberfusion/WordPressSupport/options.py
cyberfusion/WordPressSupport/plugins.py
cyberfusion/WordPressSupport/themes.py
cyberfusion/WordPressSupport/users.py
cyberfusion/WordPressSupport/wp_cli.py
python3_cyberfusion_wordpress_support-2.1.dist-info/METADATA
python3_cyberfusion_wordpress_support-2.1.dist-info/WHEEL
python3_cyberfusion_wordpress_support-2.1.dist-info/top_level.txt
python3_cyberfusion_wordpress_support-2.1.dist-info/RECORD
