Metadata-Version: 2.4
Name: python3-cyberfusion-wordpress-support
Version: 2.1
Summary: Library for WordPress.
Author-email: Cyberfusion <support@cyberfusion.io>
Project-URL: Source, https://github.com/CyberfusionIO/python3-cyberfusion-wordpress-support
Requires-Dist: python3-cyberfusion-common~=2.12
